Metadata-Version: 1.1
Name: django-python-interpreter
Version: 0.0.1
Summary: Django application for running python code in your project's environment from django admin.
Home-page: https://github.com/xzmeng/django-python-interpreter
Author: Meng Xiangzhuo
Author-email: 15195891330@163.com
License: MIT
Download-URL: https://github.com/xzmeng/django-python-interpreter/tarball/master
Platform: UNKNOWN
Classifier: Development Status :: 5 - Production/Stable
Classifier: Environment :: Web Environment
Classifier: Framework :: Django
Classifier: Intended Audience :: Developers
Classifier: License :: OSI Approved :: MIT License
Classifier: Operating System :: OS Independent
Classifier: Programming Language :: Python
Classifier: Programming Language :: Python :: 2
Classifier: Programming Language :: Python :: 3
Classifier: Topic :: Software Development :: Libraries :: Python Modules
